<?xml version="1.0" encoding="UTF-8" standalone="yes"?>
<spheres>
    <sphere>

        <!--niebieskie wypolerowane aluminium -->
        <id>niebieskie wypolerowane aluminium</id>
        <initialData>
            <centerPoint>
                <x>-5.0</x>
                <y>-5.0</y>
                <z>-10</z>
            </centerPoint>
            <radius>10</radius>
            <colorR>1</colorR>
            <colorG>1</colorG>
            <colorB>255</colorB>
        </initialData>
        <lightParams>
            <lightPosition>
                <x>-30.0</x>
                <y>-20.0</y>
                <z>-300.0</z>
            </lightPosition>
            <kd>0.13</kd>
            <ks>0.87</ks>
            <n>100</n>
        </lightParams>
    </sphere>

    <sphere>
        <id>zloty chrom</id>
        <initialData>
            <centerPoint>
                <x>-5.0</x>
                <y>-5.0</y>
                <z>-10</z>
            </centerPoint>
            <radius>10</radius>
            <colorR>100</colorR>
            <colorG>100</colorG>
            <colorB>1</colorB>
        </initialData>
        <lightParams>
            <lightPosition>
                <x>-30.0</x>
                <y>-20.0</y>
                <z>-300.0</z>
            </lightPosition>
            <kd>0.35</kd>
            <ks>0.65</ks>
            <n>10</n>
        </lightParams>
    </sphere>

    <sphere>
        <id>granit</id>
        <initialData>
            <centerPoint>
                <x>-5.0</x>
                <y>-5.0</y>
                <z>-10</z>
            </centerPoint>
            <radius>10</radius>
            <colorR>10</colorR>
            <colorG>10</colorG>
            <colorB>10</colorB>
        </initialData>
        <lightParams>
            <lightPosition>
                <x>-30.0</x>
                <y>-20.0</y>
                <z>-300.0</z>
            </lightPosition>
            <kd>0.75</kd>
            <ks>0.25</ks>
            <n>5</n>
        </lightParams>
    </sphere>
    <sphere>
        <id>brązowa kartka</id>
        <initialData>
            <centerPoint>
                <x>-5.0</x>
                <y>-5.0</y>
                <z>-10</z>
            </centerPoint>
            <radius>10</radius>
            <colorR>222</colorR>
            <colorG>184</colorG>
            <colorB>135</colorB>
        </initialData>
        <lightParams>
            <lightPosition>
                <x>-30.0</x>
                <y>-20.0</y>
                <z>-300.0</z>
            </lightPosition>
            <kd>0.9</kd>
            <ks>0.1</ks>
            <n>1</n>
        </lightParams>
    </sphere>

</spheres>